colorednoise.py
colorednoise-2.2.0.dist-info/LICENSE.txt
colorednoise-2.2.0.dist-info/METADATA
colorednoise-2.2.0.dist-info/WHEEL
colorednoise-2.2.0.dist-info/top_level.txt
colorednoise-2.2.0.dist-info/RECORD
