Metadata-Version: 2.1
Name: colorednoise
Version: 2.2.0
Summary: Generate Gaussian (1/f)**beta noise (e.g. pink noise)
Home-page: http://github.com/felixpatzelt/colorednoise
Download-URL: https://github.com/felixpatzelt/colorednoise/archive/2.2.0.tar.gz
Author: Felix Patzelt
Author-email: felix@neuro.uni-bremen.de
License: MIT
Keywords: 1/f flicker power-law correlated colored noise generator
Classifier: Development Status :: 5 - Production/Stable
Classifier: Intended Audience :: Developers
Classifier: Intended Audience :: Education
Classifier: Intended Audience :: Science/Research
Classifier: License :: OSI Approved :: MIT License
Classifier: Programming Language :: Python :: 3
Classifier: Programming Language :: Python :: 3.6
Classifier: Programming Language :: Python :: 3.7
Classifier: Programming Language :: Python :: 3.8
Classifier: Programming Language :: Python :: 3.9
Classifier: Programming Language :: Python :: 3.10
Classifier: Topic :: Scientific/Engineering
Classifier: Topic :: Software Development :: Libraries
Classifier: Topic :: Software Development :: Libraries :: Python Modules
Requires-Python: >=3
License-File: LICENSE.txt
Requires-Dist: numpy >=1.17.0
